STAR_outliers.py
STAR_outliers_library.py
STAR_outliers_plotting_library.py
STAR_outliers_polishing_library.py
STAR_outliers_testing_library.py
STAR_outliers-0.1.12.dist-info/LICENSE.md
STAR_outliers-0.1.12.dist-info/METADATA
STAR_outliers-0.1.12.dist-info/WHEEL
STAR_outliers-0.1.12.dist-info/entry_points.txt
STAR_outliers-0.1.12.dist-info/top_level.txt
STAR_outliers-0.1.12.dist-info/RECORD
