Metadata-Version: 2.1
Name: STAR_outliers
Version: 0.1.12
Requires-Python: >=3.6,<=3.9
License-File: LICENSE.md
Requires-Dist: numpy
Requires-Dist: pandas
Requires-Dist: tqdm
Requires-Dist: scipy
Requires-Dist: mock
